pip_agents_core/__init__.py
pip_agents_core/content/__init__.py
pip_agents_core-0.0.2.dist-info/LICENSE
pip_agents_core-0.0.2.dist-info/METADATA
pip_agents_core-0.0.2.dist-info/WHEEL
pip_agents_core-0.0.2.dist-info/top_level.txt
pip_agents_core-0.0.2.dist-info/zip-safe
pip_agents_core-0.0.2.dist-info/RECORD
